LICENCE
MANIFEST.in
README.md
requirements.txt
setup.py
mycfg/__init__.py
mycfg/__main__.py
mycfg/cli.py
mycfg/const.py
mycfg/error.py
mycfg/lib.py
mycfg/main.py
mycfg/meta.py
mycfg/parser.py
mycfg/state.py
mycfg.egg-info/PKG-INFO
mycfg.egg-info/SOURCES.txt
mycfg.egg-info/dependency_links.txt
mycfg.egg-info/entry_points.txt
mycfg.egg-info/requires.txt
mycfg.egg-info/top_level.txt
mycfg/obj/__init__.py
mycfg/obj/environment.py
mycfg/obj/group.py
mycfg/obj/unit.py