Metadata-Version: 2.1
Name: mycfg
Version: 1.1.9
Summary: A basic dotfiles manager
Home-page: https://github.com/pjones123/MyCfg
Author: pjones123
Author-email: pjones-uk@outlook.com
License: UNKNOWN
Keywords: dotfiles
Platform: UNKNOWN
Classifier: Environment :: Console
Classifier: Operating System :: POSIX :: Linux
Classifier: License :: OSI Approved :: GNU General Public License v3 (GPLv3)
Classifier: Natural Language :: English
Classifier: Intended Audience :: End Users/Desktop
Requires-Python: >=3.6
License-File: LICENCE
